{"v":"5.4.3","fr":30,"ip":0,"op":60,"w":2048,"h":2048,"nm":"subtract_loop_var1","ddd":0,"assets":[],"layers":[{"ddd":0,"ind":1,"ty":3,"nm":"ctrl","sr":1,"ks":{"o":{"a":0,"k":0,"ix":11},"r":{"a":0,"k":0,"ix":10},"p":{"a":0,"k":[1024,1024,0],"ix":2},"a":{"a":0,"k":[0,0,0],"ix":1},"s":{"a":0,"k":[400,400,100],"ix":6}},"ao":0,"ip":0,"op":61,"st":0,"bm":0},{"ddd":0,"ind":2,"ty":4,"nm":"sub","parent":3,"sr":1,"ks":{"o":{"a":0,"k":100,"ix":11},"r":{"a":1,"k":[{"i":{"x":[0.16],"y":[1]},"o":{"x":[0.84],"y":[0]},"n":["0p16_1_0p84_0"],"t":15,"s":[0],"e":[180]},{"t":45}],"ix":10},"p":{"a":0,"k":[0,0.69,0],"ix":2},"a":{"a":0,"k":[0,-23.814,0],"ix":1},"s":{"a":1,"k":[{"i":{"x":[0.16,0.16,0.16],"y":[1,1,1]},"o":{"x":[0.84,0.84,0.84],"y":[0,0,0]},"n":["0p16_1_0p84_0","0p16_1_0p84_0","0p16_1_0p84_0"],"t":0,"s":[100,100,100],"e":[90,90,100]},{"i":{"x":[0.16,0.16,0.16],"y":[1,1,1]},"o":{"x":[0.84,0.84,0.84],"y":[0,0,0]},"n":["0p16_1_0p84_0","0p16_1_0p84_0","0p16_1_0p84_0"],"t":30,"s":[90,90,100],"e":[100,100,100]},{"t":60}],"ix":6}},"ao":0,"shapes":[{"ty":"gr","it":[{"ind":0,"ty":"sh","ix":1,"ks":{"a":0,"k":{"i":[[0,0],[0,0]],"o":[[0,0],[0,0]],"v":[[256,-256],[-256,-256]],"c":true},"ix":2},"nm":"Path 1","mn":"ADBE Vector Shape - Group","hd":false},{"ty":"tm","s":{"a":0,"k":0,"ix":1},"e":{"a":0,"k":100,"ix":2},"o":{"a":0,"k":0,"ix":3},"m":1,"ix":2,"nm":"Trim Paths 1","mn":"ADBE Vector Filter - Trim","hd":false},{"ty":"st","c":{"a":0,"k":[0.7607843137254902,0.21176470588235294,0.08627450980392157,1],"ix":3},"o":{"a":0,"k":100,"ix":4},"w":{"a":0,"k":481,"ix":5},"lc":1,"lj":1,"ml":4,"ml2":{"a":0,"k":4,"ix":8},"bm":0,"nm":"Stroke 1","mn":"ADBE Vector Graphic - Stroke","hd":false},{"ty":"tr","p":{"a":0,"k":[0,0],"ix":2},"a":{"a":0,"k":[0,0],"ix":1},"s":{"a":0,"k":[42.745,9.302],"ix":3},"r":{"a":0,"k":0,"ix":6},"o":{"a":0,"k":100,"ix":7},"sk":{"a":0,"k":0,"ix":4},"sa":{"a":0,"k":0,"ix":5},"nm":"Transform"}],"nm":"Rectangle 1","np":3,"cix":2,"bm":0,"ix":1,"mn":"ADBE Vector Group","hd":false}],"ip":0,"op":61,"st":0,"bm":0},{"ddd":0,"ind":3,"ty":4,"nm":"back","parent":1,"sr":1,"ks":{"o":{"a":0,"k":100,"ix":11},"r":{"a":0,"k":0,"ix":10},"p":{"a":0,"k":[0,0,0],"ix":2},"a":{"a":0,"k":[0,0,0],"ix":1},"s":{"a":0,"k":[100,100,100],"ix":6}},"ao":0,"shapes":[{"ty":"gr","it":[{"ty":"gr","it":[{"ind":0,"ty":"sh","ix":1,"ks":{"a":0,"k":{"i":[[9.02,22.806],[0.158,0.391],[0.447,1.057],[24.416,20.315],[0.19,0.157],[0.656,0.528],[0.628,0.493],[0.217,0.169],[46.245,0],[0.034,0],[36.646,-45.343],[0,-47.682],[-110.457,0],[-35.832,53.944],[-0.152,0.232],[0,40.647]],"o":[[-0.155,-0.392],[-0.43,-1.066],[-12.561,-29.685],[-0.19,-0.158],[-0.649,-0.536],[-0.622,-0.5],[-0.216,-0.17],[-33.877,-26.385],[-0.033,0],[-62.79,0],[-27.792,34.388],[0,110.586],[69.56,0],[0.153,-0.231],[20.787,-31.578],[0,-26.02]],"v":[[186.02,-73.985],[185.543,-75.155],[184.237,-78.346],[127.747,-154.363],[127.18,-154.842],[125.214,-156.427],[123.349,-157.926],[122.695,-158.161],[0,-200],[-0.1,-200],[-155.551,-125.885],[-200,-0.167],[0,200],[166.647,110.464],[167.095,109.746],[200,-0.292]],"c":true},"ix":2},"nm":"Path 1","mn":"ADBE Vector Shape - Group","hd":false},{"ty":"fl","c":{"a":0,"k":[0.768627464771,0.796078443527,0.823529422283,1],"ix":4},"o":{"a":0,"k":100,"ix":5},"r":1,"bm":0,"nm":"Fill 1","mn":"ADBE Vector Graphic - Fill","hd":false},{"ty":"tr","p":{"a":0,"k":[0,0],"ix":2},"a":{"a":0,"k":[0,0],"ix":1},"s":{"a":0,"k":[100,100],"ix":3},"r":{"a":0,"k":0,"ix":6},"o":{"a":0,"k":100,"ix":7},"sk":{"a":0,"k":0,"ix":4},"sa":{"a":0,"k":0,"ix":5},"nm":"Transform"}],"nm":"Group 1","np":2,"cix":2,"bm":0,"ix":1,"mn":"ADBE Vector Group","hd":false},{"ty":"tr","p":{"a":0,"k":[0,0],"ix":2},"a":{"a":0,"k":[0,0],"ix":1},"s":{"a":0,"k":[100,100],"ix":3},"r":{"a":0,"k":0,"ix":6},"o":{"a":0,"k":100,"ix":7},"sk":{"a":0,"k":0,"ix":4},"sa":{"a":0,"k":0,"ix":5},"nm":"Transform"}],"nm":"Group 2","np":1,"cix":2,"bm":0,"ix":1,"mn":"ADBE Vector Group","hd":false}],"ip":0,"op":61,"st":0,"bm":0}],"markers":[]}